{
  "project_info": {
    "project_number": "1010026253078",
    "firebase_url": "https://irdg-31760.firebaseio.com",
    "project_id": "irdg-31760",
    "storage_bucket": "irdg-31760.appspot.com"
  },
  "client": [
    {
      "client_info": {
        "mobilesdk_app_id": "1:1010026253078:android:6716189654bd2097",
        "android_client_info": {
          "package_name": "com.irdgdc"
        }
      },
      "oauth_client": [
        {
          "client_id": "1010026253078-4dcfqqu7e3kst8os63mrki3h6h3um05m.apps.googleusercontent.com",
          "client_type": 3
        }
      ],
      "api_key": [
        {
          "current_key": "AIzaSyBRA7IRHhjVSqw514zOBiZ6xpLRW91aUIY"
        }
      ],
      "services": {
        "analytics_service": {
          "status": 1
        },
        "appinvite_service": {
          "status": 1,
          "other_platform_oauth_client": []
        },
        "ads_service": {
          "status": 2
        }
      }
    }
  ],
  "configuration_version": "1"
}